ml12/__init__.py
ml12-0.1.dist-info/METADATA
ml12-0.1.dist-info/WHEEL
ml12-0.1.dist-info/top_level.txt
ml12-0.1.dist-info/RECORD
