Metadata-Version: 2.1
Name: ml12
Version: 0.1
Summary: A custom Python package with multiple programs.
Home-page: UNKNOWN
Author: 25/25 in lab
Author-email: your_email@example.com
License: UNKNOWN
Platform: UNKNOWN
Requires-Python: >=3.6
